pixegami_hellos/__init__.py
pixegami_hellos/app.py
pixegami_hellos/cam_db_config.py
pixegami_hellos/main.py
pixegami_hellos/organizations.py
pixegami_hellos/providers.py
pixegami_hellos/z.py
pixegami_hellos-3.45.dist-info/METADATA
pixegami_hellos-3.45.dist-info/WHEEL
pixegami_hellos-3.45.dist-info/top_level.txt
pixegami_hellos-3.45.dist-info/RECORD
