Metadata-Version: 2.1
Name: pixegami_hellos
Version: 3.45
Requires-Dist: Flask
Requires-Dist: Flask-SQLAlchemy
